LICENSE
image_to_excel/VERSION
image_to_excel/__init__.py
image_to_excel/__main__.py
image_to_excel/_helpers/__init__.py
image_to_excel/_helpers/nice_logger.py
image_to_excel/base.py
image_to_excel/cli.py
image_to_excel/core/__init__.py
image_to_excel/core/excel.py
image_to_excel/core/image.py
image_to_excel/py.typed
image_to_excel-1.0.3.dist-info/entry_points.txt
image_to_excel-1.0.3.dist-info/LICENSE
image_to_excel-1.0.3.dist-info/WHEEL
image_to_excel-1.0.3.dist-info/METADATA
image_to_excel-1.0.3.dist-info/RECORD
