Metadata-Version: 2.1
Name: image-to-excel
Version: 1.0.3
Summary: A simple project to convert from an image to an excel file, because my brother wanted something that did this.
Home-page: https://github.com/alexfayers/image-to-excel
License: MIT
Author: alex.fayers
Author-email: alex@fayers.com
Requires-Python: >=3.8,<4.0
Classifier: License :: OSI Approved :: MIT License
Classifier: Programming Language :: Python :: 3
Classifier: Programming Language :: Python :: 3.8
Classifier: Programming Language :: Python :: 3.9
Classifier: Programming Language :: Python :: 3.10
Classifier: Programming Language :: Python :: 3.11
Provides-Extra: dev
Provides-Extra: devlint
Provides-Extra: docs
Provides-Extra: lint
Provides-Extra: release
Provides-Extra: test
Provides-Extra: types
Requires-Dist: numpy (>=1.23.5,<2.0.0)
Requires-Dist: pillow (>=9.3.0,<10.0.0)
Requires-Dist: pyyaml (>=6.0,<7.0)
Requires-Dist: typeguard (>=2.13.3,<3.0.0)
Requires-Dist: xlsxwriter (>=3.0.3,<4.0.0)
Project-URL: Repository, https://github.com/alexfayers/image-to-excel
